purehtml/__init__.py
purehtml/config_factory.py
purehtml/purehtml.py
purehtml/purehtml_validator.py
purehtml/backend/__init__.py
purehtml/backend/backend.py
purehtml/configs/__init__.py
purehtml/configs/configs.py
purehtml/configs/extract_params.py
purehtml/configs/selector_match_params.py
purehtml/configs/types/__init__.py
purehtml/configs/types/array_config.py
purehtml/configs/types/config_with_selector.py
purehtml/configs/types/constant_config.py
purehtml/configs/types/object_config.py
purehtml/configs/types/primitive_value_config.py
purehtml/configs/types/union_config.py
purehtml/transformers/__init__.py
purehtml/transformers/transform_params.py
purehtml/transformers/transformer.py
purehtml/transformers/transformer_factory.py
purehtml/transformers/transformers.py
purehtml/transformers/types/__init__.py
purehtml/transformers/types/attribute_transformer.py
purehtml/transformers/types/exists_transformer.py
purehtml/transformers/types/html_transformer.py
purehtml/transformers/types/length_transformer.py
purehtml/transformers/types/number_transformer.py
purehtml/transformers/types/resolve_transformer.py
purehtml/transformers/types/trim_transformer.py
purehtml/transformers/types/url_query_params_transformer.py
purehtml_purescraps-0.1.4.dist-info/LICENSE
purehtml_purescraps-0.1.4.dist-info/METADATA
purehtml_purescraps-0.1.4.dist-info/WHEEL
purehtml_purescraps-0.1.4.dist-info/top_level.txt
purehtml_purescraps-0.1.4.dist-info/RECORD
